{
  "fariType": "character",
  "lastUpdated": 1660544246,
  "name": "Urban Shadows Character Template - The Hallowed Template",
  "pages": [
    {
      "id": "ad125c44-868d-4622-9322-b6d90650841b",
      "label": "Character",
      "rows": [
        {
          "columns": [
            {
              "sections": [
                {
                  "id": "017db858-4113-4e44-b0eb-d75d90c51c94",
                  "label": "Faction:  Power\nArchetype:  The Hallowed",
                  "blocks": []
                },
                {
                  "id": "d2c67254-c64c-471e-930b-3486ad9ba0da",
                  "label": "Character Name",
                  "blocks": [
                    {
                      "id": "9a05c69c-4cf1-4508-a946-8d8db17abaa3",
                      "label": "Aaron, Amandeep, Catherine, Charity, Cornelius, Dael, Elijah, Epidiah, Gabriel,<br>Hadar, Ismail, Jade, Johnny, Kiri, Monica, Naalnish, Reta, Sarah, Shafiq, Tobias",
                      "type": "Text",
                      "value": "",
                      "meta": { "helperText": "pick one" }
                    }
                  ]
                }
              ]
            }
          ]
        },
        {
          "columns": [
            {
              "sections": [
                {
                  "id": "2fbb0016-afc7-45be-948e-5b58557b4314",
                  "label": "Look",
                  "blocks": [
                    {
                      "id": "5a7b25d8-d3d3-4340-a561-14cf4ab1be51",
                      "label": "• Ambiguous, Female, Male, Transgressing",
                      "type": "Text",
                      "value": "• Asian or South Asian, Black, Hispanic/Latino, Indigenous, Middle<br>Eastern, White, __________\n• Colorful Clothing, Ecclesiastical Clothing, Formal Clothing,<br>Simple Clothing",
                      "meta": { "helperText": "pick as many as apply" }
                    }
                  ]
                }
              ]
            },
            {
              "sections": [
                {
                  "id": "95766523-dfd6-4af2-9065-1abbcc075213",
                  "label": "Demeanor",
                  "blocks": [
                    {
                      "id": "881c2884-630f-4f2c-9c3b-c4b60ad746d3",
                      "label": "Arrogant, Casual, Clerical, Profane",
                      "type": "Text",
                      "value": "",
                      "meta": { "helperText": "pick one" }
                    }
                  ]
                }
              ]
            }
          ]
        },
        {
          "columns": [
            {
              "sections": [
                {
                  "id": "f036a20b-6415-44f7-bafa-30cbb1001fcd",
                  "label": "Intro Questions",
                  "blocks": [
                    {
                      "id": "9fb77261-36fd-4a2f-ac75-792802af6eb4",
                      "label": "Info Text",
                      "type": "InfoText",
                      "value": "• Who are you?<br><br>• How long have you been in the city?<br><br>• When did your faith first choose you?<br><br>• What hypocrisy do you hide from your flock?<br><br>• What religious mystery are you pursuing in the city?<br><br>",
                      "meta": {}
                    }
                  ]
                }
              ]
            }
          ]
        },
        {
          "columns": [
            {
              "sections": [
                {
                  "id": "4e62d3b0-a9ac-424d-beb8-8a27654782a4",
                  "label": "Starting Character Stats",
                  "blocks": [
                    {
                      "id": "67b79f69-3515-4cfd-8347-2b66e9649fea",
                      "label": "Info Text",
                      "type": "InfoText",
                      "value": "(Add 1 to one of these)",
                      "meta": {}
                    },
                    {
                      "id": "9d573075-819f-48f2-bcf4-2a452030f715",
                      "label": "Blood",
                      "type": "PointCounter",
                      "meta": { "isMainPointCounter": false },
                      "value": "0"
                    },
                    {
                      "id": "ac5f4722-a26d-44b8-9918-b5e0fc417150",
                      "label": "Heart",
                      "type": "PointCounter",
                      "meta": { "isMainPointCounter": false },
                      "value": "1"
                    },
                    {
                      "id": "0c74b86b-e10b-45c9-a588-04bf0bd290c6",
                      "label": "Mind",
                      "type": "PointCounter",
                      "meta": { "isMainPointCounter": false },
                      "value": "-2"
                    },
                    {
                      "id": "03e666e2-4064-4603-b49f-0c18aece8a78",
                      "label": "Spirit",
                      "type": "PointCounter",
                      "meta": { "isMainPointCounter": false },
                      "value": "2"
                    },
                    {
                      "id": "e03be2ca-c5d5-46ef-95c5-b70f938abcf0",
                      "label": "",
                      "type": "Separator",
                      "meta": { "hasLabel": false },
                      "value": ""
                    }
                  ]
                }
              ]
            },
            {
              "sections": [
                {
                  "id": "0bb95983-f5ed-4b28-a72f-87e7e8184ecb",
                  "label": "Starting Factions ",
                  "blocks": [
                    {
                      "id": "256c19c6-1512-4fcc-b919-8bb8de7680e4",
                      "label": "Info Text",
                      "type": "InfoText",
                      "value": "(Add 1 to one of these)",
                      "meta": {}
                    },
                    {
                      "id": "4207ceec-0889-49ad-ad9e-30b11a429b95",
                      "label": "Mortality",
                      "type": "PointCounter",
                      "meta": { "isMainPointCounter": false },
                      "value": "1"
                    },
                    {
                      "id": "e62d2f0f-7a65-4603-8217-ba66d54829f4",
                      "label": "Night",
                      "type": "PointCounter",
                      "meta": { "isMainPointCounter": false },
                      "value": "0"
                    },
                    {
                      "id": "200eb5ec-3e56-4431-a600-bc4e93e8b944",
                      "label": "Power",
                      "type": "PointCounter",
                      "meta": { "isMainPointCounter": false },
                      "value": "2"
                    },
                    {
                      "id": "445f7d59-3bf8-45e2-a2d8-817ee8606e77",
                      "label": "Wild",
                      "type": "PointCounter",
                      "meta": { "isMainPointCounter": false },
                      "value": "-2"
                    },
                    {
                      "id": "77ad14ca-08aa-40a8-846f-ea1ad3272625",
                      "label": "",
                      "type": "Separator",
                      "meta": { "hasLabel": false },
                      "value": ""
                    }
                  ]
                }
              ]
            }
          ]
        },
        {
          "columns": [
            {
              "sections": [
                {
                  "id": "89769a30-184a-4c22-b836-b1a8315c8d31",
                  "label": "Gear",
                  "blocks": [
                    {
                      "id": "21b73d4c-04d7-455f-bf91-8d3e730848ab",
                      "label": "A spartan apartment or communal living space, a prominent symbol of your<br>religious faith: a holy relic, religious tool, or arcane artifact",
                      "type": "Text",
                      "value": "",
                      "meta": {}
                    }
                  ]
                }
              ]
            }
          ]
        }
      ]
    },
    {
      "id": "d5d258ac-ade4-4a53-8f6f-8f87d5810cb1",
      "rows": [
        {
          "columns": [
            {
              "sections": [
                {
                  "id": "3f27692e-1090-4e2b-a0a0-df66c69fb484",
                  "label": "The Flock",
                  "blocks": [
                    {
                      "id": "076de1db-3982-4548-a824-8349ee976fb6",
                      "label": "You lead a religious or spiritual community that meets regularly to profess<br>their faith. The community is (choose 1): an informal and unbounded group,<br>a long-standing religious institution, a spontaneous gathering of a traditional<br>faith, a new age business, a school or university prayer group, an activist secular organization\n<br>You meet at (choose 1): \na church basement, a rec center, a member’s home, a local diner, an underground hideaway, anywhere you can find space\n<br>Your rituals and traditions are: esoteric and confusing, traditional and expected, spontaneous and energetic, solemn and restrained, genuine and improvised\n<br>Your flock is connected to you through a psychic link that offers you unparalleled access: you can let it out to try to listen in on specific members’ thoughts; cash in Debts as if a member of your flock was right in front of<br>you; call your flock to action at a distance; or even mark corruption to take on the physical appearance of a member of your flock for a scene.\n<br>At the start of each session, take one Debt against your flock as a whole, provided you were available to perform your religious duties; you can cash the<br>Debt in with any member of your flock, even other PCs.\n<br>By default, your flock consists of about fifteen seriously committed followers<br>with a few resources (cash, connections, weapons, etc.) and a deep belief in<br>your particular faith (1-harm group medium scattered devout 0-armor). Then,<br>choose 2:\n<br>•Your flock embodies the fury and righteousness of their faith. +1 harm.<br>•Your flock enjoys a modicum of faith-based direct protection against the world. +1 armor.<br>•Your flock has an explicit hierarchy or organization that serves your needs. Change +scattered to +organized.<br>•Your flock has important connections throughout the city, even within supernatural communities. Take +1 ongoing to hit the streets with Power, provided you use the flock’s network and contacts.<br>•Your flock relies on you to perform important religious rituals more often than normal. Take an additional Debt at the start of each session, provided you performed those rituals.",
                      "type": "Text",
                      "value": "",
                      "meta": {}
                    }
                  ]
                },
                {
                  "id": "3772b57c-1dda-4d8f-b465-a2e10e0b8b3a",
                  "label": "Tenets of Your Faith",
                  "blocks": [
                    {
                      "id": "f74552d9-3490-41ea-b941-8c83b85585c9",
                      "label": "Your followers are committed far more to the faith you wield than to you personally, at least at first. Choose 2 tenets of your faith that they observe nearly without fail as devout members of your traditions:\n<br>• Life is precious and unique; kill none of god’s children.<br>• True faith is spoken freely; deny not the faith nor the flock.<br>• God is god above all; give no fealty except to god.<br>• The weak demand protection; deny not a righteous request.<br>• Lies blemish the righteous; bear not false witness.\n<br>Violating any tenet of your faith in the presence of your flock—or if they find out later that you violated one of the tenets—immediately gives them a Debt over you. Any member of the flock can cash in the Debt with you, even if they weren’t the one who witnessed or discovered the violation.",
                      "type": "Text",
                      "value": "",
                      "meta": {}
                    }
                  ]
                }
              ]
            }
          ]
        }
      ],
      "label": "The Flock"
    },
    {
      "id": "e499276d-2756-465b-8ef3-cedcc77f5ccc",
      "rows": [
        {
          "columns": [
            {
              "sections": [
                {
                  "id": "9211844b-a32f-4d8f-9ccf-004789de9500",
                  "label": "Section",
                  "blocks": [
                    {
                      "id": "b61fed43-a46e-4dc2-b2a2-24df449edf3e",
                      "label": "Faint",
                      "type": "Numeric",
                      "value": "1",
                      "meta": { "checked": false }
                    },
                    {
                      "id": "a09459be-6b09-4a13-8afa-d9a9aced4a1d",
                      "label": "Faint",
                      "type": "Numeric",
                      "value": "1",
                      "meta": { "checked": false }
                    },
                    {
                      "id": "1ff2dc77-772e-46eb-9f42-28a957d5e3cd",
                      "label": "Grievous",
                      "type": "Numeric",
                      "value": "2",
                      "meta": { "checked": false }
                    },
                    {
                      "id": "8e85896e-bd0b-4bcf-8af0-a09d826f6689",
                      "label": "Grievous",
                      "type": "Numeric",
                      "value": "2",
                      "meta": { "checked": false }
                    },
                    {
                      "id": "221e7917-2a9e-4610-9abc-8d1b94b78890",
                      "label": "Critical",
                      "type": "Numeric",
                      "value": "3",
                      "meta": { "checked": false }
                    },
                    {
                      "id": "38532052-5716-4e33-b621-2d66294ff354",
                      "label": "Critical",
                      "type": "Numeric",
                      "value": "3",
                      "meta": { "checked": false }
                    }
                  ]
                },
                {
                  "id": "51c5c34c-5a1c-49bb-823d-990d4c92e5c7",
                  "label": "Section",
                  "blocks": [
                    {
                      "id": "c5c11ef5-1461-4329-867c-c583c6f9b6f2",
                      "label": "Current Armor Rating",
                      "type": "PointCounter",
                      "meta": { "isMainPointCounter": false },
                      "value": "0"
                    }
                  ]
                }
              ]
            },
            {
              "sections": [
                {
                  "id": "92fc75d0-ca7d-480b-ac6c-bf0e4f9c534a",
                  "label": "Section",
                  "blocks": [
                    {
                      "id": "516cb1e5-ec1c-4732-bc2c-a601197581b0",
                      "label": "Incapacitated",
                      "type": "Numeric",
                      "value": "1",
                      "meta": { "checked": false }
                    }
                  ]
                },
                {
                  "id": "89fa03fa-af11-4e06-8ec9-4b9dad151a94",
                  "label": "Section",
                  "blocks": [
                    {
                      "id": "528c6f26-aec3-4346-9774-5fb91b299d1d",
                      "label": "Shattered (-1 Blood)",
                      "type": "SlotTracker",
                      "meta": {
                        "helperText": "Shattered means frightened, weakened, and overly cautious. Shattered characters hesitate when they should move, and their attempts to unleash an<br>attack on someone or escape a situation often come up short."
                      },
                      "value": [{ "label": "", "checked": false }]
                    },
                    {
                      "id": "b5a9ea37-c306-4e19-a9fc-383053dea05c",
                      "label": "Crushed (-1 Heart)",
                      "type": "SlotTracker",
                      "meta": {
                        "helperText": "Crushed means traumatized, timid, and uncertain. Crushed characters bear<br>the full weight of the wounds they’ve suffered, and their attempts to persuade an NPC are inhibited by their reticent approach to conflict."
                      },
                      "value": [{ "label": "", "checked": false }]
                    },
                    {
                      "id": "616f37d1-f3cc-48c6-8aa2-05f2bf7c6a84",
                      "label": "Fractured (-1 Mind)",
                      "type": "SlotTracker",
                      "meta": {
                        "helperText": "Fractured means confused, disoriented, and disjointed. Fractured characters<br>are unstable and unsure, and their attempts to figure someone out or mislead, distract, or trick others are unfocused and imprecise."
                      },
                      "value": [{ "label": "", "checked": false }]
                    },
                    {
                      "id": "a3cc060e-e826-46bf-bda4-c21c55d5f35b",
                      "label": "Broken (-1 Spirit)",
                      "type": "SlotTracker",
                      "meta": {
                        "helperText": "Broken means hopeless, forlorn, and cowardly. Broken characters have lost<br>their will to fight, and their attempts to keep their cool or let it out are often<br>half-hearted and incomplete."
                      },
                      "value": [{ "label": "", "checked": false }]
                    }
                  ]
                }
              ]
            }
          ]
        }
      ],
      "label": "Harm"
    },
    {
      "id": "6f63f6e3-e457-4206-ac27-2353b478cb65",
      "rows": [
        {
          "columns": [
            {
              "sections": [
                {
                  "id": "1535a4b9-1829-421e-afce-112dbda9d2cb",
                  "label": "Corruption Track",
                  "blocks": [
                    {
                      "id": "8dd06e97-d1ea-457a-9ea2-60a474467810",
                      "label": "Corruption ",
                      "type": "SlotTracker",
                      "meta": {},
                      "value": [
                        { "label": "", "checked": false },
                        { "label": "", "checked": false },
                        { "label": "", "checked": false },
                        { "label": "", "checked": false },
                        { "label": "", "checked": false }
                      ]
                    }
                  ]
                },
                {
                  "id": "5246c35a-e30e-48ef-8c1f-e05011cab564",
                  "label": "Corruption Advances",
                  "blocks": [
                    {
                      "id": "71f5cd6d-76d2-4cb1-a24a-2dfcee903086",
                      "label": "Take a corruption advance for your flock",
                      "type": "SlotTracker",
                      "meta": {},
                      "value": [{ "label": "", "checked": false }]
                    },
                    {
                      "id": "ebcce1b9-fd26-4d7d-869c-e3d707b7acaa",
                      "label": "Take a corruption advance for your flock",
                      "type": "SlotTracker",
                      "meta": {},
                      "value": [{ "label": "", "checked": false }]
                    },
                    {
                      "id": "811a5765-1589-4538-9217-6f6774f4b518",
                      "label": "Take a corruption advance for your flock",
                      "type": "SlotTracker",
                      "meta": {},
                      "value": [{ "label": "", "checked": false }]
                    },
                    {
                      "id": "2738262f-e795-4cdb-a81e-cff0bbf7fa0f",
                      "label": "Take a corruption advance from another Archetype",
                      "type": "SlotTracker",
                      "meta": {},
                      "value": [{ "label": "", "checked": false }]
                    },
                    {
                      "id": "b8580d99-8651-4a06-8cc8-90d3d3897428",
                      "label": "Change playbooks to any Mortality playbook; your flock is now a Threat",
                      "type": "SlotTracker",
                      "meta": {},
                      "value": [{ "label": "", "checked": false }]
                    }
                  ]
                }
              ]
            },
            {
              "sections": [
                {
                  "id": "7db0f478-01eb-4a21-be13-44a060cafe3a",
                  "label": "Corruption Moves",
                  "blocks": [
                    {
                      "id": "d79e09ed-389a-45b0-b9cd-d3bd5a274830",
                      "label": "Rites and Rituals",
                      "type": "Skill",
                      "value": "0",
                      "meta": {
                        "checked": false,
                        "commands": [],
                        "helperText": "&nbsp;Your flock, gathered and united, forms a powerful spiritual tool or weapon, a sanctum (Urban Shadows, page 128) that allows<br>you to perform magical rituals and create powerfully blessed objects.<br>When the GM tells you what you need to complete the ritual, you may<br>ignore one of the requirements if you convince a member of your flock to<br>give life or limb to the ceremony or mark corruption yourself.&nbsp;"
                      }
                    },
                    {
                      "id": "0e1b94dd-5c4a-4848-86ad-e5db144d9f26",
                      "label": "Augury",
                      "type": "Skill",
                      "value": "0",
                      "meta": {
                        "checked": false,
                        "commands": [],
                        "helperText": "&nbsp;Your flock, gathered and united, gives you insight into the ley<br>lines and power centers of the city; when you pray with them, you may<br>investigate a place of power at any distance, provided you are willing to<br>make an appropriate sacrifice to your faith or mark corruption.&nbsp;"
                      }
                    },
                    {
                      "id": "a31f4e67-7746-4339-bbe5-25fb6fe43fd6",
                      "label": "Infallible",
                      "type": "Skill",
                      "value": "0",
                      "meta": {
                        "checked": false,
                        "commands": [],
                        "helperText": "Your flock no longer questions your instructions or advice, following your will as best they can without violating the tenets of your faith.<br>When you call your flock to action, persuade one of its members, or<br>mislead, distract, or trick them, treat a 7-9 as a 10+ result. Mark corruption to extend this effect to requests that violate the tenets of your faith."
                      }
                    },
                    {
                      "id": "128e82bc-e780-4ffd-9246-6cefafd44202",
                      "label": "Apocalypto",
                      "type": "Skill",
                      "value": "0",
                      "meta": {
                        "checked": false,
                        "commands": [],
                        "helperText": "Your flock is truly prepared for days of trial and tribulation:<br>add +1 size, +1 armor, +1 harm, and +fanatical. At the end of a session,<br>mark corruption if you did not lead your flock in punishing unbelievers or<br>heretics during the session."
                      }
                    }
                  ]
                }
              ]
            }
          ]
        }
      ],
      "label": "Corruption"
    },
    {
      "id": "c6690e9b-eb36-42c0-aa05-026c0915d264",
      "rows": [
        {
          "columns": [
            {
              "sections": [
                {
                  "id": "7b944ee0-4738-4859-9b3a-3f89aa5a7681",
                  "label": "Debts",
                  "blocks": [
                    {
                      "id": "ebf405b3-8e79-436b-bea0-37278291638c",
                      "label": "• You destroyed or banished something (or someone) important at<br>the request of another character. They owe you a Debt.",
                      "type": "Text",
                      "value": "",
                      "meta": {}
                    },
                    {
                      "id": "2920ab2a-85d9-4787-93f4-3081e0dc171e",
                      "label": "• Someone comes to you often to confess their sins and seek forgiveness. Tell them what solace you offer, and ask them if they are comforted by your offering. If they find your efforts sufficient,<br>they owe you a Debt; if you come up short, you owe them a Debt.",
                      "type": "Text",
                      "value": "",
                      "meta": {}
                    },
                    {
                      "id": "ffa6cfb2-f302-46e1-b199-b757c35b66f7",
                      "label": "• Someone is intimately engaged with a member of your flock, but<br>you doubt they have your follower’s best interests at heart. They<br>owe you a Debt.",
                      "type": "Text",
                      "value": "",
                      "meta": {}
                    }
                  ]
                }
              ]
            }
          ]
        },
        {
          "columns": [
            {
              "sections": [
                {
                  "id": "0975eba5-9abb-42fd-b5d7-0b1dca69eeee",
                  "label": "Hallowed Moves",
                  "blocks": [
                    {
                      "id": "4a45b2a3-7007-438a-a1f9-1fb6a612e098",
                      "label": "Shepherd",
                      "type": "Skill",
                      "value": "0",
                      "meta": {
                        "checked": false,
                        "commands": ["2d6"],
                        "helperText": "When you call your flock to action in keeping with your faith,<br>roll + Spirit. On a 10+, all three. On a 7-9, choose 1:<br>• They all honor your request for action<br>• They don’t ask any difficult questions<br>• They don’t demand a Debt from you<br>On a miss, a portion of your flock is seized by the faith and moves to<br>address the problem in ways you did not foresee",
                        "hideModifier": false
                      }
                    },
                    {
                      "id": "2a7f1f6e-7f4c-49d4-8912-928269fb0739",
                      "label": "Info Text",
                      "type": "InfoText",
                      "value": "And choose two more:",
                      "meta": {}
                    },
                    {
                      "id": "3cb5eaa7-3755-4992-b1ac-4e1ccd78353c",
                      "label": "Sanctified",
                      "type": "Skill",
                      "value": "0",
                      "meta": {
                        "checked": false,
                        "commands": ["2d6"],
                        "helperText": "When you bestow the blessings of your faith on another,<br>roll with Spirit. On a hit, your faith envelops them: heal them (2-harm),<br>bestow protection (+1 armor), or anoint an item they carry (+blessed),<br>your choice. On a 10+, also choose 1 from below. On a 7-9, choose 2.<br>• You mark corruption<br>• You suffer 1-harm (ap)<br>• They are marked by your faith<br>On a miss, your faith reveals something terrible about the intended target<br>of your gifts. You must take all three to complete the blessing.&nbsp;"
                      }
                    }
                  ]
                }
              ]
            },
            {
              "sections": [
                {
                  "id": "4b4bf20b-6171-4f32-88dd-7fa91ab03b98",
                  "label": "Drama Moves",
                  "blocks": [
                    {
                      "id": "3955b635-9b1b-46d7-80b6-700ecc64c0dc",
                      "label": "Hallowed Corruption Move<br>",
                      "type": "Text",
                      "value": "",
                      "meta": {
                        "helperText": "When you violate the tenets of your faith (or through inaction allow them to<br>be violated), mark corruption."
                      }
                    },
                    {
                      "id": "cf49b084-2f44-48b7-83d1-4d30f1051221",
                      "label": "Hallowed Intimacy Move<br>",
                      "type": "Text",
                      "value": "",
                      "meta": {
                        "helperText": "When you share a moment of intimacy—physical or emotional—with another<br>person, you choose whether or not their intimacy move triggers. If it doesn’t,<br>tell them what mark or aspect of your faith keeps you distant from them."
                      }
                    },
                    {
                      "id": "c315ab84-6a3f-4e04-b136-78c7473c457d",
                      "label": "Hallowed End Move<br>",
                      "type": "Text",
                      "value": "",
                      "meta": {
                        "helperText": "When you die, you perform a powerful miracle of your faith. The innocent<br>may rise, the wicked may fall, so on and so forth. You cannot prevent your<br>own death."
                      }
                    }
                  ]
                }
              ]
            }
          ]
        }
      ],
      "label": "Moves"
    },
    {
      "id": "64ef910e-2163-4ab8-a743-dbd30051cc8a",
      "rows": [
        {
          "columns": [
            {
              "sections": [
                {
                  "id": "928cd3f1-9790-4a1e-bc63-1355fd53ac9d",
                  "label": "Standard Avances",
                  "blocks": [
                    {
                      "id": "2ed6480a-4c3b-42d2-ba37-5cd82186d880",
                      "label": "+1 Blood (max +3) ",
                      "type": "SlotTracker",
                      "meta": {},
                      "value": [{ "label": "", "checked": false }]
                    },
                    {
                      "id": "b22e430d-1bb6-4786-b8c4-9bcd8421e928",
                      "label": "+1 Heart (max +3)",
                      "type": "SlotTracker",
                      "meta": {},
                      "value": [{ "label": "", "checked": false }]
                    },
                    {
                      "id": "2453a9df-ccce-4df7-b93d-a188b96280c9",
                      "label": "+1 Mind (max +3)",
                      "type": "SlotTracker",
                      "meta": {},
                      "value": [{ "label": "", "checked": false }]
                    },
                    {
                      "id": "12cafeb2-0225-40f3-98b7-4cd79e3e5276",
                      "label": "+1 Spirit (max +3)",
                      "type": "SlotTracker",
                      "meta": {},
                      "value": [{ "label": "", "checked": false }]
                    },
                    {
                      "id": "edc279fa-886d-4831-9920-f4d66bdbca59",
                      "label": "Add a feature to your flock",
                      "type": "SlotTracker",
                      "meta": {},
                      "value": [{ "label": "", "checked": false }]
                    },
                    {
                      "id": "40daa7a8-31e4-44b2-804a-6acca8be83e1",
                      "label": "Add a feature to your flock",
                      "type": "SlotTracker",
                      "meta": {},
                      "value": [{ "label": "", "checked": false }]
                    },
                    {
                      "id": "fee00b3f-295d-48c1-8e13-648a964c4cb6",
                      "label": "A move from another Archetype",
                      "type": "SlotTracker",
                      "meta": {},
                      "value": [{ "label": "", "checked": false }]
                    },
                    {
                      "id": "e624d00b-a775-41ea-b149-7488847e6864",
                      "label": "A move from another Archetype",
                      "type": "SlotTracker",
                      "meta": {},
                      "value": [{ "label": "", "checked": false }]
                    },
                    {
                      "id": "371d4992-4ca0-4459-b01f-390627c5fdd6",
                      "label": "Erase a corruption advance",
                      "type": "SlotTracker",
                      "meta": {},
                      "value": [{ "label": "", "checked": false }]
                    },
                    {
                      "id": "4daac97c-c6dd-43f9-909c-93790895327c",
                      "label": "Change your Faction",
                      "type": "SlotTracker",
                      "meta": {},
                      "value": [{ "label": "", "checked": false }]
                    }
                  ]
                }
              ]
            },
            {
              "sections": [
                {
                  "id": "a4fee955-02cc-4134-98a7-87e74be471a2",
                  "label": "Cont...",
                  "blocks": [
                    {
                      "id": "a02eb838-86c4-4cb8-8747-b638996a31a5",
                      "label": "Info Text",
                      "type": "InfoText",
                      "value": "After 5 advances you may select:",
                      "meta": {}
                    },
                    {
                      "id": "aea94363-0911-4bd4-89a0-bead930a6f86",
                      "label": "+1 to any stat (max +3)",
                      "type": "SlotTracker",
                      "meta": {},
                      "value": [{ "label": "", "checked": false }]
                    },
                    {
                      "id": "c2ef0cd0-37bd-41f1-b99a-c0b409ba63cf",
                      "label": "+1 to any Faction (max +3)",
                      "type": "SlotTracker",
                      "meta": {},
                      "value": [{ "label": "", "checked": false }]
                    },
                    {
                      "id": "0096cdd1-e484-47f8-9a28-c7e7bf6b9f39",
                      "label": "Erase a scar",
                      "type": "SlotTracker",
                      "meta": {},
                      "value": [{ "label": "", "checked": false }]
                    },
                    {
                      "id": "2d97ad96-7490-44e2-a438-137c0b5377ce",
                      "label": "Erase a corruption advance",
                      "type": "SlotTracker",
                      "meta": {},
                      "value": [{ "label": "", "checked": false }]
                    },
                    {
                      "id": "28a70f96-0cb3-4f4a-b36e-1472604369af",
                      "label": "Change to a new Archetype",
                      "type": "SlotTracker",
                      "meta": {},
                      "value": [{ "label": "", "checked": false }]
                    },
                    {
                      "id": "801d8d09-fe12-410f-9f57-d059968d0807",
                      "label": "Retire your character to safety",
                      "type": "SlotTracker",
                      "meta": {},
                      "value": [{ "label": "", "checked": false }]
                    },
                    {
                      "id": "7bb295e0-50a4-4f32-b142-c725ecbcb59e",
                      "label": "Advance 3 basic moves",
                      "type": "SlotTracker",
                      "meta": {},
                      "value": [{ "label": "", "checked": false }]
                    },
                    {
                      "id": "377d61f6-937e-4ae1-9794-1cc404b31973",
                      "label": "Advance 3 basic moves",
                      "type": "SlotTracker",
                      "meta": {},
                      "value": [{ "label": "", "checked": false }]
                    },
                    {
                      "id": "18c20624-f927-4a05-9b4b-addc6d9375f3",
                      "label": "Take Channeling and three Spells",
                      "type": "SlotTracker",
                      "meta": {},
                      "value": [{ "label": "", "checked": false }]
                    }
                  ]
                }
              ]
            }
          ]
        }
      ],
      "label": "Advances"
    }
  ],
  "template": "Blank",
  "version": 6,
  "wide": true,
  "group": "Urban Shadows Archetypes"
}
