{"fariType":"character","lastUpdated":1654987224,"name":"Tales of Xadia Template","pages":[{"id":"b7355fe2-ce3f-4b43-9eee-731bdac6aa5c","rows":[{"columns":[{"sections":[{"id":"605779ac-b2e2-4f4b-9b90-168441d00ece","label":"Character","blocks":[{"id":"6347d601-964f-4b87-953b-0f18570b7016","type":"Text","value":"","meta":{"helperText":"Name"}},{"id":"0642dc60-d47e-4c5b-b4f2-9abdee6154ad","type":"Text","value":"","meta":{"helperText":"Archetype"}},{"id":"ec618168-4321-4461-be4f-0aed1d4ff28d","type":"Text","value":"","meta":{"helperText":"Pronouns"}}],"visibleOnCard":true}]},{"sections":[{"id":"162ccebe-0cd4-4006-b14d-54311f1c9ce3","label":"","blocks":[{"id":"36fdfd58-359f-4e5c-b17b-8752f95dd5fd","label":"","type":"Image","meta":{},"value":""}]}]}]},{"columns":[{"sections":[{"id":"730cdd99-4b00-45d8-b538-f28b1748863c","label":"Plot Points","blocks":[{"id":"ca17368f-0340-47c0-9b83-335fea864125","label":"Plot Points","type":"PointCounter","meta":{"isMainPointCounter":true},"value":"1"}]}]}]}],"label":"Character"},{"id":"2d6a5edc-2be8-4ddc-8df9-6b07151fb699","label":"Traits","rows":[{"columns":[{"sections":[{"id":"bc6438c8-fceb-418e-a0bd-1adc0af64cca","label":"Attributes","blocks":[{"id":"a37804b8-fbd2-4525-a98d-a3218dc2c237","label":"Agility","type":"DicePool","value":"","meta":{"commands":["1d4"],"width":0.33,"helperText":"Your hand-eye coordination. Use this when you need to fight, sneak, aim, or balance.<br>"}},{"id":"a1580965-b38a-4667-af41-8eaa87452078","label":"Awareness","type":"DicePool","value":"","meta":{"commands":["1d4"],"width":0.33,"helperText":"Your ability to perceive your\n<br>surroundings and other people. Use this as you pay att ention to the world around you.<br>"}},{"id":"1a8b7dcb-ba5d-4824-9518-2646caa350e4","label":"Influence","type":"DicePool","value":"","meta":{"commands":["1d4"],"width":0.33,"helperText":": Your presence and persuasiveness. Use this while you convince, coerce, charm, or\n<br>collude.<br>"}},{"id":"6729cb2e-6e87-497d-8c8f-d87f3a3f0b69","label":"Intellect","type":"DicePool","value":"","meta":{"commands":["1d4"],"width":0.33,"helperText":"Your capacity to comprehend. Use this to study, learn, recall things you know, or figure\n<br>out a puzzle.<br>"}},{"id":"bdeabc45-a60e-4c0c-8ba4-54e4c49211ed","label":"Spirit","type":"DicePool","value":"","meta":{"commands":["1d4"],"width":0.33,"helperText":"Your mental resolve and emotional reserves. Use this when the situation requires\n<br>courage, determination, perseverance, or willpower.<br>"}},{"id":"7cbab079-a2e4-4bc4-93c0-8099196965be","label":"Strenght","type":"DicePool","value":"","meta":{"commands":["1d4"],"width":0.33,"helperText":"Your level of physical fi tness and power. Use this if you’re called to be tough, strong, or use brute force.<br>"}}]}]}]},{"columns":[{"sections":[{"id":"7934ca76-700d-4a94-8625-07295a5232ee","label":"Values","blocks":[{"id":"e459b0dd-1539-420f-9c04-1fc17860a30b","label":"Devotion","type":"DicePool","value":"","meta":{"commands":["1d4"],"width":0.33,"helperText":"Duty, faith, and friendship. You’re motivated by the bonds of&nbsp;loyalty and your love for others.<br>"}},{"id":"218148a6-f903-4779-8120-8922fcd61292","label":"Libery","type":"DicePool","value":"","meta":{"commands":["1d4"],"width":0.33,"helperText":"Freedom, independence, and autonomy. You’re motivated\n<br>by a world without oppression or suppression.<br>"}},{"id":"693d8930-e515-4a0e-a141-ae42ca44b8e7","label":"Glory","type":"DicePool","value":"","meta":{"commands":["1d4"],"width":0.33,"helperText":"Legacy, fame, and fortune. You’re motivated by praise, acclaim, and your desire to be remembered.<br>"}},{"id":"89fb9211-6970-4efc-826c-d0d668fd868f","label":"Mastery","type":"DicePool","value":"","meta":{"commands":["1d4"],"width":0.33,"helperText":"Control, achievement, and skill. You’re motivated by power, growth, and self-development.<br>"}},{"id":"11f8f8a7-6492-4cf4-986d-d5052cae2f44","label":"Justice","type":"DicePool","value":"","meta":{"commands":["1d4"],"width":0.33,"helperText":"Balance, righteousness, and reward. You’re motivated by adherence to fairness and what you think is right.<br>"}},{"id":"964128f6-1c29-454e-8520-18af2a3c7e1e","label":"Truth","type":"DicePool","value":"","meta":{"commands":["1d4"],"width":0.33,"helperText":"Fidelity, certainty, and authenticity. You’re motivated by finding strength in facts and by the principle and pursuit of knowledge.<br>"}}]}]}]},{"columns":[{"sections":[{"id":"ecb4fb15-6754-49e4-92b8-953508cea02d","label":"Distinctions","blocks":[{"id":"0726c3f4-e5f5-4b36-a2ab-907ff450513c","label":"Kindred","type":"DicePool","value":"","meta":{"commands":["1d8"],"width":0.33}},{"id":"85c84b1d-413d-412e-b349-0c4477f9fdf7","label":"Where Are You From?","type":"Text","value":"\n","meta":{"width":0.5,"helperText":"Your kindred distinction reflects where you grew up and what sort of community you belonged to when you were coming of age.<br>"}},{"id":"91f2537b-a6be-444c-8655-90b154209c1e","label":"","type":"Separator","meta":{"hasLabel":false},"value":""},{"id":"d6f7cca1-1636-433a-b903-b06691c7e754","label":"Vocation","type":"DicePool","value":"","meta":{"commands":["1d8"],"width":0.33}},{"id":"224d30da-9eaf-44a2-8193-affa640eeccc","label":"How Were You Trained?\r\r\n","type":"Text","value":"","meta":{"width":0.5,"helperText":"Your vocation distinction represents what you chose to do with your life at a young age, making it part of your youth and upbringing.<br>"}},{"id":"dc519f24-bf99-4390-9477-a8e4d24274f7","label":"","type":"Separator","meta":{"hasLabel":false},"value":""},{"id":"71399f56-107b-4701-bf18-50bd4fd11595","label":"Quirk","type":"DicePool","value":"","meta":{"commands":["1d8"],"width":0.33}},{"id":"79c851bb-2991-46b3-be0f-2954e4d35e88","label":"What Makes You Different?\r\n","type":"Text","value":"","meta":{"width":0.5,"helperText":"Your quirk distinction, more than any adjective or description, best encapsulates who your character is in regard to everyone else you’re likely to meet.<br>"}},{"id":"03abad64-0fee-4598-ba18-757c192a5192","label":"","type":"Separator","meta":{"hasLabel":false},"value":""},{"id":"2434733c-636a-4a4e-8e3d-8724e02d6e83","label":"Hinder","type":"DicePool","value":"","meta":{"commands":["1d4"],"width":1,"helperText":"Gain one plot point when you use Hinder by switching out this distinction’s die rating for a d4.<br>"}}],"visibleOnCard":false}]}]},{"columns":[{"sections":[{"id":"d505720d-c76f-4e73-b5d6-c9f865eebc0f","label":"Special Effects\r\n","blocks":[{"id":"b5245a43-da8d-463d-a52d-731be55a351a","label":"Info Text","type":"InfoText","value":"SFX are special benefits or tricks. Activating them usually requires a cost, such as spending a Plot Point. These effects only last for the duration of the roll you’re using them on, unless otherwise specified.<br>","meta":{}},{"id":"d476774f-66e6-42d5-af1e-096766829925","label":"SFX","type":"Text","value":"","meta":{}},{"id":"1aa0bfa2-1ca3-4359-abf9-cf3a6d127063","label":"SFX","type":"Text","value":"","meta":{}}]}]}]},{"columns":[{"sections":[{"id":"8624f81f-ac1e-4eae-80c7-d6e89e53ae43","label":"Specialties","blocks":[{"id":"00a10775-c105-4687-bea1-efcb37e01ab1","label":"Info Text","type":"InfoText","value":"A specialty is rated from d6 to d12 and covers a narrow field of expertise or ability. You can include these dice in your dice pool when you roll so long as what you’re doing is relevant to the specialty’s area.<br>","meta":{}},{"id":"978a86fb-db5b-44d8-a105-c27dec41e28b","label":"Specialty","type":"DicePool","value":"","meta":{"commands":["1d6"],"width":0.33}},{"id":"2137e9db-a34a-4927-b1f9-fb94f1ee78b8","label":"Specialty","type":"DicePool","value":"","meta":{"commands":["1d6"],"width":0.33}},{"id":"2804c928-61ca-45d4-b51f-ffa23d925632","label":"Specialty","type":"DicePool","value":"","meta":{"commands":["1d6"],"width":0.33}}]},{"id":"0b528a4a-6a29-4339-9ff4-b932003d5fe3","label":"Assets","blocks":[{"id":"ec1e2be8-0d22-40e8-b3c6-f71abbc35d1e","label":"Info Text","type":"InfoText","value":"An asset is rated from d6 to d12 and is something or someone who can assist you that isn’t inherent or part of you.<br>","meta":{}},{"id":"ceec4471-fb55-44f9-9b4c-6ceb1e5d4d11","label":"Asset","type":"DicePool","value":"","meta":{"commands":["1d6"],"width":0.33}},{"id":"addabc8b-e286-4e25-8748-fd94b3bbdffa","label":"Asset","type":"DicePool","value":"","meta":{"commands":["1d6"],"width":0.33}},{"id":"9c8d5363-d498-4b65-aea0-5746ecde3c26","label":"Asset","type":"DicePool","value":"","meta":{"commands":["1d6"],"width":0.33}}]}]}]}]},{"id":"ee5ebdde-32ae-4d72-aee3-be8c61eab41c","rows":[{"columns":[{"sections":[{"id":"ae2ca5fd-6f90-4505-9f0f-d7ed4d47c4a7","label":"Afraid","blocks":[{"id":"6147e486-bd28-4483-a0f3-1de203e0d583","label":"Info Text","type":"InfoText","value":"This is the stress of fear and panic. Once this exceeds d12, you are gripped in the clutches of terror.<br>","meta":{}},{"id":"226cb6eb-eddd-4271-a0c9-34c8c1b18d4b","label":"Stress","type":"DicePool","value":"","meta":{"commands":[],"width":0.5}},{"id":"55591b1a-1d21-4e76-885a-d353b12da6d4","label":"Trauma","type":"DicePool","value":"","meta":{"commands":[],"width":0.5}}]}]},{"sections":[{"id":"f65d83a7-bf07-4d82-87e2-39a475c15c99","label":"Corrupted","blocks":[{"id":"e3b737ef-7ea3-4f69-80f9-967de789a5fd","label":"Info Text","type":"InfoText","value":"This is the stress of dark magic. Once this exceeds d12, you are consumed with darkness.<br>","meta":{}},{"id":"beadc94a-9bf1-4755-8011-fab27be88c0b","label":"Stress","type":"DicePool","value":"","meta":{"commands":[],"width":0.5}},{"id":"c862a4bf-660a-4eaa-b8c2-f7200d70cdb8","label":"Trauma","type":"DicePool","value":"","meta":{"commands":[],"width":0.5}}]}]}]},{"columns":[{"sections":[{"id":"35747ea8-1680-4844-9fee-7a0e5d839795","label":"Insecure","blocks":[{"id":"c993eb95-8c81-4151-9abe-b59895b88d89","label":"Info Text","type":"InfoText","value":"This is the stress of apprehension and worry. Once this exceeds d12, you succumb to insecurity.<br>","meta":{}},{"id":"71d0727d-a98d-413c-ae58-9faec81853a5","label":"Stress","type":"DicePool","value":"","meta":{"commands":[],"width":0.5}},{"id":"6786a2fb-95c2-4d27-b4e9-5ac9225f4056","label":"Trauma","type":"DicePool","value":"","meta":{"commands":[],"width":0.5}}]}]},{"sections":[{"id":"25ac4c7d-73fa-44d9-962a-055ca45b8091","label":"Angry","blocks":[{"id":"32662d31-4463-4533-ac82-6e978fd6d08b","label":"Info Text","type":"InfoText","value":"This is the stress of rage and frustration. Once this exceeds d12, you are lost to your wrath.<br>","meta":{}},{"id":"60d5383a-7777-4968-af56-d2f814fab5af","label":"Stress","type":"DicePool","value":"","meta":{"commands":[],"width":0.5}},{"id":"38f42cd1-a8b0-4582-92e5-7483e38cbec7","label":"Trauma","type":"DicePool","value":"","meta":{"commands":[],"width":0.5}}]}]}]},{"columns":[{"sections":[{"id":"2f86c04c-f370-4626-b0d1-e118e0d559a1","label":"Exhausted","blocks":[{"id":"94280cba-f3f7-4812-8b9a-4156613dd762","label":"Info Text","type":"InfoText","value":"This is the stress of fatigue and weariness. Once this exceeds d12, you can no longer remain awake.<br>","meta":{}},{"id":"2ef76839-0a4d-4bac-b82d-0a157c040f8d","label":"Stress","type":"DicePool","value":"","meta":{"commands":[],"width":0.5}},{"id":"8352fd5a-bde5-4681-bf46-5351de7cc159","label":"Trauma","type":"DicePool","value":"","meta":{"commands":[],"width":0.5}}]}]},{"sections":[{"id":"0b087ef8-eb32-4119-9be4-42e4419da8b3","label":"Injured","blocks":[{"id":"0193012a-3612-4a0e-8433-cfbe3ccdd4be","label":"Info Text","type":"InfoText","value":"This is the stress of pain and wounding. Once this exceeds d12, you collapse unconscious and may die.<br>","meta":{}},{"id":"72d19077-5d68-4826-ba2f-9a6cd08da0e1","label":"Stress","type":"DicePool","value":"","meta":{"commands":[],"width":0.5}},{"id":"5647742f-d21e-4f11-bf34-4a5c63569d98","label":"Trauma","type":"DicePool","value":"","meta":{"commands":[],"width":0.5}}]}]}]}],"label":"Stress &amp; Trauma"}],"template":"Blank","version":6,"wide":false,"theme":{"backgroundColor":"#fdfae8","sectionHeadingFontFamily":"'Marcellus', serif;","style":"@import url('https://fonts.googleapis.com/css2?family=Marcellus&display=swap');","helperTextFontSize":0.75,"infoTextFontSize":0.875,"textFontFamily":"'Marcellus', serif;","textFontSize":1.75,"hideSectionBackground":false,"sectionHeadingFontSize":1.75,"helperTextFontWeight":"","labelFontSize":1.5,"pageHeadingFontFamily":"'Roboto', sans-serif;","labelFontFamily":"'Roboto', sans-serif;","infoTextFontFamily":"'Roboto', sans-serif;","helperTextFontFamily":"'Roboto', sans-serif;"}}